colormap_complex/__init__.py
colormap_complex/_main.py
colormap_complex/matplotlib.py
colormap_complex/py.typed
colormap_complex/data/bremm.npy
colormap_complex/data/cubediagonal.npy
colormap_complex/data/schumann.npy
colormap_complex/data/steiger.npy
colormap_complex/data/teulingfig2.npy
colormap_complex/data/ziegler.npy
colormap_complex-0.2.0.dist-info/licenses/LICENSE
colormap_complex-0.2.0.dist-info/METADATA
colormap_complex-0.2.0.dist-info/WHEEL
colormap_complex-0.2.0.dist-info/top_level.txt
colormap_complex-0.2.0.dist-info/RECORD
