Metadata-Version: 2.4
Name: colormap-complex
Version: 0.2.0
Summary: Complex / 2d colormap / Domain coloring for matplotlib etc.
Author-email: 34j <34j.95a2p@simplelogin.com>
License: Apache-2.0
Project-URL: Bug Tracker, https://github.com/34j/colormap-complex/issues
Project-URL: Changelog, https://github.com/34j/colormap-complex/blob/main/CHANGELOG.md
Project-URL: documentation, https://colormap-complex.readthedocs.io
Project-URL: repository, https://github.com/34j/colormap-complex
Classifier: Development Status :: 2 - Pre-Alpha
Classifier: Intended Audience :: Developers
Classifier: Natural Language :: English
Classifier: Operating System :: OS Independent
Classifier: Programming Language :: Python :: 3.9
Classifier: Programming Language :: Python :: 3.10
Classifier: Programming Language :: Python :: 3.11
Classifier: Programming Language :: Python :: 3.12
Classifier: Programming Language :: Python :: 3.13
Classifier: Topic :: Software Development :: Libraries
Requires-Python: >=3.10
License-File: LICENSE
Requires-Dist: colour-science>=0.4.4
Requires-Dist: pytest-xdist>=3.6.1
Dynamic: license-file
